valigator/__about__.py
valigator/__init__.py
valigator/mailutils.py
valigator/utils.py
valigator/valigator.py
valigator-0.1.2.dist-info/DESCRIPTION.rst
valigator-0.1.2.dist-info/METADATA
valigator-0.1.2.dist-info/RECORD
valigator-0.1.2.dist-info/WHEEL
valigator-0.1.2.dist-info/entry_points.txt
valigator-0.1.2.dist-info/metadata.json
valigator-0.1.2.dist-info/pbr.json
valigator-0.1.2.dist-info/top_level.txt
