Metadata-Version: 2.0
Name: valigator
Version: 0.1.2
Summary: Validate your backups !
Home-page: https://github.com/deviantony/valigator
Author: Anthony Lapenna
Author-email: lapenna.anthony@gmail.com
License: MIT
Keywords: database backup docker
Platform: UNKNOWN
Classifier: Intended Audience :: System Administrators
Classifier: Topic :: System :: Archiving :: Backup
Classifier: License :: OSI Approved :: Apache Software License
Classifier: Programming Language :: Python :: 3
Classifier: Programming Language :: Python :: 3.4
Requires-Dist: PyYAML
Requires-Dist: bottle
Requires-Dist: docker-py
